[
  {
    "id": 1,
    "title": "Spaghetti Carbonara",
    "summary": "A classic Italian pasta dish with eggs, cheese, bacon, and black pepper.",
    "image": "https://via.placeholder.com/400x250",
    "ingredients": ["Spaghetti", "Eggs", "Parmesan Cheese", "Bacon", "Black Pepper"],
    "instructions": [
      "Boil the pasta until al dente.",
      "Fry the bacon until crisp.",
      "Whisk eggs and cheese in a bowl.",
      "Combine pasta, bacon, and egg mixture. Serve warm."
    ]
  },
  {
    "id": 2,
    "title": "Chicken Tikka Masala",
    "summary": "Grilled chicken chunks cooked in a creamy tomato sauce.",
    "image": "https://via.placeholder.com/400x250",
    "ingredients": ["Chicken", "Tomatoes", "Cream", "Garlic", "Spices"],
    "instructions": [
      "Marinate chicken with spices and yogurt.",
      "Grill until slightly charred.",
      "Prepare tomato-based sauce with cream.",
      "Mix grilled chicken into sauce and simmer."
    ]
  }
]

